optimus_prime/__init__.py
optimus_prime/attend.py
optimus_prime/autoregressive_wrapper.py
optimus_prime/continuous_autoregressive_wrapper.py
optimus_prime/flash.py
optimus_prime/nonautoregressive_wrapper.py
optimus_prime/x_transformers.py
optimus_prime/xl_autoregressive_wrapper.py
optimus_prime_transformers-1.2.1.dist-info/LICENSE
optimus_prime_transformers-1.2.1.dist-info/METADATA
optimus_prime_transformers-1.2.1.dist-info/WHEEL
optimus_prime_transformers-1.2.1.dist-info/top_level.txt
optimus_prime_transformers-1.2.1.dist-info/RECORD
