Metadata-Version: 2.1
Name: optimus-prime-transformers
Version: 1.2.1
Summary: optimus-prime - Pytorch
Home-page: https://github.com/kyegomez/Optimus-Prime
Author: Kye Gomez
Author-email: kye@apac.ai
License: MIT
Keywords: artificial intelligence,attention mechanism,transformers
Classifier: Development Status :: 4 - Beta
Classifier: Intended Audience :: Developers
Classifier: Topic :: Scientific/Engineering :: Artificial Intelligence
Classifier: License :: OSI Approved :: MIT License
Classifier: Programming Language :: Python :: 3.6
License-File: LICENSE
Requires-Dist: torch
Requires-Dist: einops
